MANIFEST.in
README.md
README.txt
setup.py
whoshere/__init__.py
whoshere/conf.py
whoshere/mtargets.py
whoshere/utils.py
whoshere/webhandler.py
whoshere/whoshere.py
whoshere/whoshere_main.py
whoshere-iftt/README.md
whoshere-iftt/whoshere-iftt.py
whoshere-isy/README.md
whoshere-isy/whoshere-isy.py
whoshere.egg-info/PKG-INFO
whoshere.egg-info/SOURCES.txt
whoshere.egg-info/dependency_links.txt
whoshere.egg-info/entry_points.txt
whoshere.egg-info/requires.txt
whoshere.egg-info/top_level.txt